brown_phototour_revisited/__init__.py
brown_phototour_revisited/_nbdev.py
brown_phototour_revisited/benchmarking.py
brown_phototour_revisited/dataset.py
brown_phototour_revisited/extraction.py
brown_phototour_revisited-0.3.0.dist-info/LICENSE
brown_phototour_revisited-0.3.0.dist-info/METADATA
brown_phototour_revisited-0.3.0.dist-info/WHEEL
brown_phototour_revisited-0.3.0.dist-info/top_level.txt
brown_phototour_revisited-0.3.0.dist-info/RECORD
