Metadata-Version: 2.1
Name: brown-phototour-revisited
Version: 0.3.0
Summary: The package for local patch descriptors evaluation, which takes into account image indexes and second nearest neighbor ratio (SNN) filtering strategy. It is in agreement with IMC benchmark and practice, unlike the original protocol.
Home-page: https://github.com/ducha-aiki/brown_phototour_revisited/tree/master/
Author: Dmytro Mishkin
Author-email: ducha.aiki@gmail.com
License: Apache Software License 2.0
Keywords: evaluation,local patches,local descriptors,SIFT,HardNet
Classifier: Development Status :: 4 - Beta
Classifier: Intended Audience :: Developers
Classifier: License :: OSI Approved :: Apache Software License
Classifier: Natural Language :: English
Classifier: Programming Language :: Python :: 3.6
Classifier: Programming Language :: Python :: 3.7
Classifier: Programming Language :: Python :: 3.8
Requires-Python: >=3.6
License-File: LICENSE
